[
  {
    "ContainingType": "CrmApp.Api.Controllers.ClienteController",
    "Method": "Post",
    "RelativePath": "api/clientes",
    "HttpMethod": "POST",
    "IsController": true,
    "Order": 0,
    "Parameters": [
      {
        "Name": "dto",
        "Type": "CrmApp.Application.DTOs.CriarClienteDTO",
        "IsRequired": true
      }
    ],
    "ReturnTypes": []
  },
  {
    "ContainingType": "CrmApp.Api.Controllers.ClienteController",
    "Method": "Get",
    "RelativePath": "api/clientes/{id}",
    "HttpMethod": "GET",
    "IsController": true,
    "Order": 0,
    "Parameters": [
      {
        "Name": "id",
        "Type": "System.Guid",
        "IsRequired": true
      }
    ],
    "ReturnTypes": []
  }
]